Sources/__init__.py
Sources/el_wikipedia.py
entitylinkin_wikipedia-0.0.1.dist-info/METADATA
entitylinkin_wikipedia-0.0.1.dist-info/WHEEL
entitylinkin_wikipedia-0.0.1.dist-info/top_level.txt
entitylinkin_wikipedia-0.0.1.dist-info/RECORD
