Metadata-Version: 2.1
Name: entitylinkin-wikipedia
Version: 0.0.1
Summary: Package for Entity Linking using WikiPedia
Author: Soumyadipta Maiti
Author-email: soumya55555@gmail.com
Keywords: Python,Entity Linking,NER,WikiPedia
Classifier: Development Status :: 1 - Planning
Classifier: Intended Audience :: Developers
Classifier: Programming Language :: Python :: 3
Classifier: Operating System :: Unix
Classifier: Operating System :: MacOS :: MacOS X
Classifier: Operating System :: Microsoft :: Windows
Requires-Dist: pandas
Requires-Dist: spacy
Requires-Dist: spacy-entity-linker
